energydatamodel/__init__.py
energydatamodel/abstract.py
energydatamodel/base.py
energydatamodel/battery.py
energydatamodel/building.py
energydatamodel/collection.py
energydatamodel/geospatial.py
energydatamodel/heatpump.py
energydatamodel/hydro.py
energydatamodel/powergrid.py
energydatamodel/solar.py
energydatamodel/timeseries.py
energydatamodel/weathersensor.py
energydatamodel/wind.py
energydatamodel-0.0.3.dist-info/licenses/LICENCE.md
energydatamodel-0.0.3.dist-info/METADATA
energydatamodel-0.0.3.dist-info/WHEEL
energydatamodel-0.0.3.dist-info/top_level.txt
energydatamodel-0.0.3.dist-info/RECORD
