Metadata-Version: 2.4
Name: energydatamodel
Version: 0.0.3
Summary: Data model for energy modelling.
Author: rebase.energy
License: MIT
Project-URL: homepage, https://energydatamodel.org
Project-URL: repository, https://github.com/rebase-energy/EnergyDataModel
Project-URL: documentation, https://docs.energydatamodel.org/en/latest
Requires-Python: >=3.11
License-File: LICENCE.md
Requires-Dist: anytree>=2.12.1
Requires-Dist: build>=1.2.2.post1
Requires-Dist: geopandas>=1.0.1
Requires-Dist: matplotlib>=3.10.1
Requires-Dist: pandas==2.2.2
Requires-Dist: pvlib>=0.12.0
Requires-Dist: pytz>=2025.1
Requires-Dist: shapely>=2.0.7
Provides-Extra: dev
Requires-Dist: ipykernel>=6.29.5; extra == "dev"
Requires-Dist: ipywidgets>=8.1.5; extra == "dev"
Requires-Dist: sphinx==7.2.6; extra == "dev"
Requires-Dist: sphinx-autodoc-typehints>=2.0.1; extra == "dev"
Requires-Dist: sphinx-rtd-theme>=3.0.2; extra == "dev"
Dynamic: license-file
